[
  {
    "timestamp": 1763218711408,
    "user": "Rezz",
    "userId": "spotify:user:31ilktz5fqv575vybtkzthcniyqu",
    "track": "penjaga hati",
    "artist": "Nadhif Basalamah",
    "uri": "spotify:track:6i9Ci0IN1q1GcnhdbKU7kZ",
    "imageUrl": "https://i.scdn.co/image/ab67616d0000b27325001f594384ffb7fb952347"
  },
  {
    "timestamp": 1763218450950,
    "user": "Rezz",
    "userId": "spotify:user:31ilktz5fqv575vybtkzthcniyqu",
    "track": "Mencintaimu",
    "artist": "Sal Priadi",
    "uri": "spotify:track:26aNjbOgTVrFZEx7was69A",
    "imageUrl": "https://i.scdn.co/image/ab67616d0000b273489cd3228dbaa5552e5ed8c9"
  },
  {
    "timestamp": 1763218176484,
    "user": "Rezz",
    "userId": "spotify:user:31ilktz5fqv575vybtkzthcniyqu",
    "track": "Rumpang",
    "artist": "Nadin Amizah",
    "uri": "spotify:track:2TRGNVokPnC2a2oHg5iv1H",
    "imageUrl": "https://i.scdn.co/image/ab67616d0000b27397068c79ef4ad5a7643ef94a"
  },
  {
    "timestamp": 1763217852864,
    "user": "Rezz",
    "userId": "spotify:user:31ilktz5fqv575vybtkzthcniyqu",
    "track": "Rehat",
    "artist": "Kunto Aji",
    "uri": "spotify:track:7mjO4RbTZIb1SfE8G673Lm",
    "imageUrl": "https://i.scdn.co/image/ab67616d0000b273b7d74c7fa660999ad4ff0e8d"
  },
  {
    "timestamp": 1763217497061,
    "user": "Rezz",
    "userId": "spotify:user:31ilktz5fqv575vybtkzthcniyqu",
    "track": "Sinyal-Sinyal",
    "artist": "Bernadya",
    "uri": "spotify:track:2VjlTuNUGwJJCch2XtUnrb",
    "imageUrl": "https://i.scdn.co/image/ab67616d0000b273cb1e5f7d0942bf9196c1e711"
  },
  {
    "timestamp": 1763217267056,
    "user": "Rezz",
    "userId": "spotify:user:31ilktz5fqv575vybtkzthcniyqu",
    "track": "Tenang",
    "artist": "Yura Yunita",
    "uri": "spotify:track:7lr82r1RMJudgcKQ8y7H9K",
    "imageUrl": "https://i.scdn.co/image/ab67616d0000b27368d7905b0548a6c9ba21b638"
  },
  {
    "timestamp": 1763217018308,
    "user": "Rezz",
    "userId": "spotify:user:31ilktz5fqv575vybtkzthcniyqu",
    "track": "Kusut",
    "artist": "Fourtwnty",
    "uri": "spotify:track:3diD8b3u6oEn74BezQpujj",
    "imageUrl": "https://i.scdn.co/image/ab67616d0000b27395d6a28dfd9d8da037c142df"
  },
  {
    "timestamp": 1763216757664,
    "user": "Rezz",
    "userId": "spotify:user:31ilktz5fqv575vybtkzthcniyqu",
    "track": "Yasudah",
    "artist": "Sal Priadi",
    "uri": "spotify:track:3qhj6auEMIDhJv6oCHI9fJ",
    "imageUrl": "https://i.scdn.co/image/ab67616d0000b273686acaaa87bfc6ebb42b3bd2"
  },
  {
    "timestamp": 1763216471898,
    "user": "Rezz",
    "userId": "spotify:user:31ilktz5fqv575vybtkzthcniyqu",
    "track": "Mendarah",
    "artist": "Nadin Amizah",
    "uri": "spotify:track:75OokMC3JzPnRNXcLTAKdr",
    "imageUrl": "https://i.scdn.co/image/ab67616d0000b2736d57a5c60decaa8fb39d5afb"
  },
  {
    "timestamp": 1763216218528,
    "user": "Rezz",
    "userId": "spotify:user:31ilktz5fqv575vybtkzthcniyqu",
    "track": "Berlari",
    "artist": "Bernadya",
    "uri": "spotify:track:3xQx7JqDSUk8q36W68BVEM",
    "imageUrl": "https://i.scdn.co/image/ab67616d0000b27327693aaf059002bba3a7655a"
  },
  {
    "timestamp": 1763212137392,
    "user": "Rezz",
    "userId": "spotify:user:31ilktz5fqv575vybtkzthcniyqu",
    "track": "Kasih Aba Aba",
    "artist": "Naykilla, Tenxi, Jemsii",
    "uri": "spotify:track:5rhwXZP0luMucnEPnYJpbI",
    "imageUrl": "https://i.scdn.co/image/ab67616d0000b2738afa25403ff8a518ee7a9f94"
  },
  {
    "timestamp": 1763209751302,
    "user": "Rezz",
    "userId": "spotify:user:31ilktz5fqv575vybtkzthcniyqu",
    "track": "Calon Mantu Idaman (feat. Ncum)",
    "artist": "Rombongan Bodonk Koplo, Ncum",
    "uri": "spotify:track:5EWyweCJ5igLl6bjbGRmGm",
    "imageUrl": "https://i.scdn.co/image/ab67616d0000b2732120cd815e807ae193648e7e"
  },
  {
    "timestamp": 1763209465910,
    "user": "Rezz",
    "userId": "spotify:user:31ilktz5fqv575vybtkzthcniyqu",
    "track": "Penyangkalan",
    "artist": "For Revenge",
    "uri": "spotify:track:3GdN5n6p34yFMd12WKq8jL",
    "imageUrl": "https://i.scdn.co/image/ab67616d0000b2730b2982815e3f47c2fb7b74c4"
  },
  {
    "timestamp": 1763209196790,
    "user": "Rezz",
    "userId": "spotify:user:31ilktz5fqv575vybtkzthcniyqu",
    "track": "back to friends",
    "artist": "sombr",
    "uri": "spotify:track:0FTmksd2dxiE5e3rWyJXs6",
    "imageUrl": "https://i.scdn.co/image/ab67616d0000b2739d24f74c1e2d8a12b1e591ec"
  },
  {
    "timestamp": 1763208776116,
    "user": "Rezz",
    "userId": "spotify:user:31ilktz5fqv575vybtkzthcniyqu",
    "track": "Orang Baru Lebe Gacor",
    "artist": "Ecko Show, Juan Reza, Chesylino",
    "uri": "spotify:track:3dANqzstXrnHIUh1r7JrGZ",
    "imageUrl": "https://i.scdn.co/image/ab67616d0000b273e650a23cce85ff0f02a0d61f"
  },
  {
    "timestamp": 1763208451826,
    "user": "Rezz",
    "userId": "spotify:user:31ilktz5fqv575vybtkzthcniyqu",
    "track": "Orang Baru Lebe Gacor",
    "artist": "Ecko Show, Juan Reza, Chesylino",
    "uri": "spotify:track:3dANqzstXrnHIUh1r7JrGZ",
    "imageUrl": "https://i.scdn.co/image/ab67616d0000b273e650a23cce85ff0f02a0d61f"
  },
  {
    "timestamp": 1763207292833,
    "user": "Rezz",
    "userId": "spotify:user:31ilktz5fqv575vybtkzthcniyqu",
    "track": "Tanpa Cinta",
    "artist": "Yovie Widianto, Tiara Andini",
    "uri": "spotify:track:3CSFXGhoR8C9kBF90xhIXG",
    "imageUrl": "https://i.scdn.co/image/ab67616d0000b273d1b4ab00a8b44b4405f884e0"
  },
  {
    "timestamp": 1763206294495,
    "user": "Rezz",
    "userId": "spotify:user:31ilktz5fqv575vybtkzthcniyqu",
    "track": "mejikuhibiniu",
    "artist": "Tenxi, Suisei, Jemsii",
    "uri": "spotify:track:278PwGlIm7MxVTZud18Rx4",
    "imageUrl": "https://i.scdn.co/image/ab67616d0000b2734d265eb3c717ab45470fdc8c"
  },
  {
    "timestamp": 1763206084698,
    "user": "Rezz",
    "userId": "spotify:user:31ilktz5fqv575vybtkzthcniyqu",
    "track": "Kita Usahakan Lagi",
    "artist": "Batas Senja",
    "uri": "spotify:track:1wfbqUSPWbnPjkiBA9UmoF",
    "imageUrl": "https://i.scdn.co/image/ab67616d0000b273246e30c4bef2c5336465aca7"
  },
  {
    "timestamp": 1763205814537,
    "user": "Rezz",
    "userId": "spotify:user:31ilktz5fqv575vybtkzthcniyqu",
    "track": "Lampu Kuning",
    "artist": "Juicy Luicy",
    "uri": "spotify:track:6Npkwd5gv61SR6QZbTyNf9",
    "imageUrl": "https://i.scdn.co/image/ab67616d0000b273fadca79809c06f6afe7de0d9"
  },
  {
    "timestamp": 1763205574760,
    "user": "Rezz",
    "userId": "spotify:user:31ilktz5fqv575vybtkzthcniyqu",
    "track": "everything u are",
    "artist": "Hindia",
    "uri": "spotify:track:5WOSNVChcadlsCRiqXE45K",
    "imageUrl": "https://i.scdn.co/image/ab67616d0000b27305898628baab6ef07a0a4d03"
  },
  {
    "timestamp": 1763205334129,
    "user": "Rezz",
    "userId": "spotify:user:31ilktz5fqv575vybtkzthcniyqu",
    "track": "Nina",
    "artist": ".Feast",
    "uri": "spotify:track:1zFaLYA10ImwEejge3F5nm",
    "imageUrl": "https://i.scdn.co/image/ab67616d0000b27339695d4c16489cdf60bef536"
  },
  {
    "timestamp": 1763205090126,
    "user": "Rezz",
    "userId": "spotify:user:31ilktz5fqv575vybtkzthcniyqu",
    "track": "Opalite",
    "artist": "Taylor Swift",
    "uri": "spotify:track:3euZKF0hmGxQ6h2JHHY4iu",
    "imageUrl": "https://i.scdn.co/image/ab67616d0000b273b034f9cdf12ae14c603daa99"
  },
  {
    "timestamp": 1763204828359,
    "user": "Rezz",
    "userId": "spotify:user:31ilktz5fqv575vybtkzthcniyqu",
    "track": "Bunga Maaf",
    "artist": "The Lantis",
    "uri": "spotify:track:26KhLgFuPymkm1uiZkc6Rv",
    "imageUrl": "https://i.scdn.co/image/ab67616d0000b27342196e31b446e21f056660eb"
  },
  {
    "timestamp": 1763204584474,
    "user": "Rezz",
    "userId": "spotify:user:31ilktz5fqv575vybtkzthcniyqu",
    "track": "Tarot",
    "artist": ".Feast",
    "uri": "spotify:track:4XHijJfABTtUCW3Bp6KFvr",
    "imageUrl": "https://i.scdn.co/image/ab67616d0000b273c800b90e2092a5328f699117"
  },
  {
    "timestamp": 1763204284294,
    "user": "Rezz",
    "userId": "spotify:user:31ilktz5fqv575vybtkzthcniyqu",
    "track": "Mangu",
    "artist": "Fourtwnty, Charita Utami",
    "uri": "spotify:track:4e6TmHCC4PRUj75knNplNP",
    "imageUrl": "https://i.scdn.co/image/ab67616d0000b27332ab17f5515e51490841f648"
  },
  {
    "timestamp": 1763203178213,
    "user": "Rezz",
    "userId": "spotify:user:31ilktz5fqv575vybtkzthcniyqu",
    "track": "Mangu",
    "artist": "Fourtwnty, Charita Utami",
    "uri": "spotify:track:4e6TmHCC4PRUj75knNplNP",
    "imageUrl": "https://i.scdn.co/image/ab67616d0000b27332ab17f5515e51490841f648"
  },
  {
    "timestamp": 1763202457244,
    "user": "Rezz",
    "userId": "spotify:user:31ilktz5fqv575vybtkzthcniyqu",
    "track": "Terbuang Dalam Waktu",
    "artist": "Barasuara",
    "uri": "spotify:track:5fmyW3X3kncOOVlmcWhORH",
    "imageUrl": "https://i.scdn.co/image/ab67616d0000b27395688e1f59ae3fc4951d41ff"
  },
  {
    "timestamp": 1763202187331,
    "user": "Rezz",
    "userId": "spotify:user:31ilktz5fqv575vybtkzthcniyqu",
    "track": "Tak Ada Ujungnya",
    "artist": "Rony Parulian",
    "uri": "spotify:track:2JekYbWANgDe54Dndi2I2C",
    "imageUrl": "https://i.scdn.co/image/ab67616d0000b2735d2e53fbcef5d8d00bed2d8d"
  },
  {
    "timestamp": 1763201977606,
    "user": "Rezz",
    "userId": "spotify:user:31ilktz5fqv575vybtkzthcniyqu",
    "track": "Lesung Pipi",
    "artist": "Raim Laode",
    "uri": "spotify:track:2OxvanM5m1Na9OVlXyXmUp",
    "imageUrl": "https://i.scdn.co/image/ab67616d0000b2732605ea6f02168bf5a74c012e"
  },
  {
    "timestamp": 1763201737357,
    "user": "Rezz",
    "userId": "spotify:user:31ilktz5fqv575vybtkzthcniyqu",
    "track": "ours to keep",
    "artist": "Kendis, adis",
    "uri": "spotify:track:3Puhw21QI2MKR4rdvyPuIb",
    "imageUrl": "https://i.scdn.co/image/ab67616d0000b27341f65131e6205f8deac33651"
  },
  {
    "timestamp": 1763201540167,
    "user": "Rezz",
    "userId": "spotify:user:31ilktz5fqv575vybtkzthcniyqu",
    "track": "TABOLA BALE",
    "artist": "Silet Open Up, Jacson Seran, Juan Reza, Diva Aurel",
    "uri": "spotify:track:6KfugJFINWqA42k59hmjFr",
    "imageUrl": "https://i.scdn.co/image/ab67616d0000b27310df7b8e9b3ed2588888a8ae"
  },
  {
    "timestamp": 1763201257218,
    "user": "Rezz",
    "userId": "spotify:user:31ilktz5fqv575vybtkzthcniyqu",
    "track": "bergema sampai selamanya",
    "artist": "Nadhif Basalamah",
    "uri": "spotify:track:1RaJdXCj61oSRUUciGKoWe",
    "imageUrl": "https://i.scdn.co/image/ab67616d0000b273b55b8d4574f736630e8469ab"
  },
  {
    "timestamp": 1763201081595,
    "user": "Rezz",
    "userId": "spotify:user:31ilktz5fqv575vybtkzthcniyqu",
    "track": "Lihat Kebunku (Taman Bunga)",
    "artist": "Aku Jeje",
    "uri": "spotify:track:5dvIK269hL3eZXQMG4Vc2C",
    "imageUrl": "https://i.scdn.co/image/ab67616d0000b273dc82bf3a920d66bd3006d308"
  },
  {
    "timestamp": 1763200867496,
    "user": "Rezz",
    "userId": "spotify:user:31ilktz5fqv575vybtkzthcniyqu",
    "track": "Sedia Aku Sebelum Hujan",
    "artist": "Idgitaf",
    "uri": "spotify:track:64qfw9JZl3RYCrq4Mn0WvT",
    "imageUrl": "https://i.scdn.co/image/ab67616d0000b2738dc8c573565969d55f9f3477"
  },
  {
    "timestamp": 1763200629060,
    "user": "Rezz",
    "userId": "spotify:user:31ilktz5fqv575vybtkzthcniyqu",
    "track": "The Fate of Ophelia",
    "artist": "Taylor Swift",
    "uri": "spotify:track:31TXxq8gfgYyrYClnYY48m",
    "imageUrl": "https://i.scdn.co/image/ab67616d0000b273b034f9cdf12ae14c603daa99"
  },
  {
    "timestamp": 1763200418423,
    "user": "Rezz",
    "userId": "spotify:user:31ilktz5fqv575vybtkzthcniyqu",
    "track": "Alamak",
    "artist": "Rizky Febian, Adrian Khalif",
    "uri": "spotify:track:1vkwlZncsYqFukl2Q7M6Fe",
    "imageUrl": "https://i.scdn.co/image/ab67616d0000b27301b9750a33d771645d7f043a"
  },
  {
    "timestamp": 1763178550852,
    "user": "Rezz",
    "userId": "spotify:user:31ilktz5fqv575vybtkzthcniyqu",
    "track": "Tanya",
    "artist": "Dere",
    "uri": "spotify:track:1TcNl9Dty9qOcq4bjIMINw",
    "imageUrl": "https://i.scdn.co/image/ab67616d0000b273719b3f4d2a462303a7b58907"
  },
  {
    "timestamp": 1763175815207,
    "user": "Rezz",
    "userId": "spotify:user:31ilktz5fqv575vybtkzthcniyqu",
    "track": "Berawal Dari Tatap",
    "artist": "Yura Yunita",
    "uri": "spotify:track:4K0YdYv8a6UC9fWi9hV5MH",
    "imageUrl": "https://i.scdn.co/image/ab67616d0000b2731e4e95c4e26e1f04580e374d"
  },
  {
    "timestamp": 1763175545115,
    "user": "Rezz",
    "userId": "spotify:user:31ilktz5fqv575vybtkzthcniyqu",
    "track": "Besok kita pergi makan",
    "artist": "Sal Priadi",
    "uri": "spotify:track:0xnzQ3Ek5X5r2pcbwIEQdc",
    "imageUrl": "https://i.scdn.co/image/ab67616d0000b273bbecdd16366f501dbec8adb4"
  },
  {
    "timestamp": 1763175364810,
    "user": "Rezz",
    "userId": "spotify:user:31ilktz5fqv575vybtkzthcniyqu",
    "track": "Mundur Perlahan",
    "artist": "Nyoman Paul",
    "uri": "spotify:track:5O42C9Cxl3p5brlN9jDbEJ",
    "imageUrl": "https://i.scdn.co/image/ab67616d0000b273d7a9692a9d8b98c9a9eb8c19"
  },
  {
    "timestamp": 1763175094868,
    "user": "Rezz",
    "userId": "spotify:user:31ilktz5fqv575vybtkzthcniyqu",
    "track": "Kalibata, 2012",
    "artist": "Perunggu",
    "uri": "spotify:track:0EQBfsLlv47ie3p0fE1QEs",
    "imageUrl": "https://i.scdn.co/image/ab67616d0000b2737b75822516f485d6fc90b60e"
  },
  {
    "timestamp": 1763174795034,
    "user": "Rezz",
    "userId": "spotify:user:31ilktz5fqv575vybtkzthcniyqu",
    "track": "menangis di jalan pulang",
    "artist": "Nadin Amizah",
    "uri": "spotify:track:4dzRG1dWHna5Klwp8AByH7",
    "imageUrl": "https://i.scdn.co/image/ab67616d0000b273144855c41fcb68b2e5519f6d"
  },
  {
    "timestamp": 1763174435077,
    "user": "Rezz",
    "userId": "spotify:user:31ilktz5fqv575vybtkzthcniyqu",
    "track": "Sepatu",
    "artist": "Tulus",
    "uri": "spotify:track:73DWDOjVUyJ8sAiAcySvgS",
    "imageUrl": "https://i.scdn.co/image/ab67616d0000b2737c52c7f7d1da8625e4376795"
  },
  {
    "timestamp": 1763174194765,
    "user": "Rezz",
    "userId": "spotify:user:31ilktz5fqv575vybtkzthcniyqu",
    "track": "penjaga hati",
    "artist": "Nadhif Basalamah",
    "uri": "spotify:track:6i9Ci0IN1q1GcnhdbKU7kZ",
    "imageUrl": "https://i.scdn.co/image/ab67616d0000b27325001f594384ffb7fb952347"
  },
  {
    "timestamp": 1763173954912,
    "user": "Rezz",
    "userId": "spotify:user:31ilktz5fqv575vybtkzthcniyqu",
    "track": "Pesan Terakhir",
    "artist": "Lyodra",
    "uri": "spotify:track:3FwQ3RYYEekzjEeL3jdpUZ",
    "imageUrl": "https://i.scdn.co/image/ab67616d0000b273d00e5994b61f1d93dafe9221"
  },
  {
    "timestamp": 1763173685127,
    "user": "Rezz",
    "userId": "spotify:user:31ilktz5fqv575vybtkzthcniyqu",
    "track": "Ada titik-titik di ujung doa",
    "artist": "Sal Priadi",
    "uri": "spotify:track:1E7zLPDdqo0OvzVmGj5aoV",
    "imageUrl": "https://i.scdn.co/image/ab67616d0000b273686acaaa87bfc6ebb42b3bd2"
  },
  {
    "timestamp": 1763173384846,
    "user": "Rezz",
    "userId": "spotify:user:31ilktz5fqv575vybtkzthcniyqu",
    "track": "Titik Nadir (feat. Monita Tahalea)",
    "artist": "Kahitna, Monita Tahalea",
    "uri": "spotify:track:52m690jqpxP1tHHkRNdl5p",
    "imageUrl": "https://i.scdn.co/image/ab67616d0000b2735cfcb24701901b0e53ce4fae"
  },
  {
    "timestamp": 1763173145206,
    "user": "Rezz",
    "userId": "spotify:user:31ilktz5fqv575vybtkzthcniyqu",
    "track": "Ah",
    "artist": "Nadin Amizah",
    "uri": "spotify:track:0huV20ZR9HzTmBtXeYpEwD",
    "imageUrl": "https://i.scdn.co/image/ab67616d0000b27394847679fe7b10e27d9803f5"
  },
  {
    "timestamp": 1763172904955,
    "user": "Rezz",
    "userId": "spotify:user:31ilktz5fqv575vybtkzthcniyqu",
    "track": "Benci Untuk Mencinta",
    "artist": "Naif",
    "uri": "spotify:track:65PjFLm6X567f52At4CI1N",
    "imageUrl": "https://i.scdn.co/image/ab67616d0000b273e4d084a54bcdd3e2feb80b68"
  },
  {
    "timestamp": 1763172668727,
    "user": "Rezz",
    "userId": "spotify:user:31ilktz5fqv575vybtkzthcniyqu",
    "track": "Dermaga",
    "artist": "Idgitaf",
    "uri": "spotify:track:4oHgB9OGBdQ0uVmWKQmiQh",
    "imageUrl": "https://i.scdn.co/image/ab67616d0000b273b549a8ecdc8adc1a6b30ca85"
  },
  {
    "timestamp": 1763172484990,
    "user": "Rezz",
    "userId": "spotify:user:31ilktz5fqv575vybtkzthcniyqu",
    "track": "Dear Diary",
    "artist": "Feby Putri",
    "uri": "spotify:track:4yDpYEuT1mQn3ZcEB1gceL",
    "imageUrl": "https://i.scdn.co/image/ab67616d0000b27343d85512e6cf43b4967b1923"
  },
  {
    "timestamp": 1763172275000,
    "user": "Rezz",
    "userId": "spotify:user:31ilktz5fqv575vybtkzthcniyqu",
    "track": "I'd like to watch you sleeping",
    "artist": "Sal Priadi",
    "uri": "spotify:track:0Y7dCFSIdB9vJ8nnVIAfuv",
    "imageUrl": "https://i.scdn.co/image/ab67616d0000b273686acaaa87bfc6ebb42b3bd2"
  },
  {
    "timestamp": 1763171974917,
    "user": "Rezz",
    "userId": "spotify:user:31ilktz5fqv575vybtkzthcniyqu",
    "track": "Langit dan Laut",
    "artist": "Banda Neira",
    "uri": "spotify:track:2R0VGwIIO28cL4Fmu6TLax",
    "imageUrl": "https://i.scdn.co/image/ab67616d0000b2737a173b7767ca05f9bb17464e"
  },
  {
    "timestamp": 1763171615033,
    "user": "Rezz",
    "userId": "spotify:user:31ilktz5fqv575vybtkzthcniyqu",
    "track": "Cermin",
    "artist": "Nadin Amizah",
    "uri": "spotify:track:2s07iRgvSgwLFr23eXFFQQ",
    "imageUrl": "https://i.scdn.co/image/ab67616d0000b2736d57a5c60decaa8fb39d5afb"
  },
  {
    "timestamp": 1763171344871,
    "user": "Rezz",
    "userId": "spotify:user:31ilktz5fqv575vybtkzthcniyqu",
    "track": "Terakhir Kali",
    "artist": "Wijaya 80",
    "uri": "spotify:track:5EZnMCsJEoMJJ6aJlVaMiP",
    "imageUrl": "https://i.scdn.co/image/ab67616d0000b273beafa800065ea92fa2b9493f"
  },
  {
    "timestamp": 1763171044866,
    "user": "Rezz",
    "userId": "spotify:user:31ilktz5fqv575vybtkzthcniyqu",
    "track": "everything u are",
    "artist": "Hindia",
    "uri": "spotify:track:5WOSNVChcadlsCRiqXE45K",
    "imageUrl": "https://i.scdn.co/image/ab67616d0000b27305898628baab6ef07a0a4d03"
  },
  {
    "timestamp": 1763170805111,
    "user": "Rezz",
    "userId": "spotify:user:31ilktz5fqv575vybtkzthcniyqu",
    "track": "Apa Mungkin - Demo Version",
    "artist": "Bernadya",
    "uri": "spotify:track:5RveogdH4YRFlW2kdGT0vA",
    "imageUrl": "https://i.scdn.co/image/ab67616d0000b2733a5d323fd49a9797ec304f1e"
  },
  {
    "timestamp": 1763170685243,
    "user": "Rezz",
    "userId": "spotify:user:31ilktz5fqv575vybtkzthcniyqu",
    "track": "Mencintaimu",
    "artist": "Sal Priadi",
    "uri": "spotify:track:26aNjbOgTVrFZEx7was69A",
    "imageUrl": "https://i.scdn.co/image/ab67616d0000b273489cd3228dbaa5552e5ed8c9"
  },
  {
    "timestamp": 1763170385258,
    "user": "Rezz",
    "userId": "spotify:user:31ilktz5fqv575vybtkzthcniyqu",
    "track": "Cinta Sendiri",
    "artist": "Kahitna",
    "uri": "spotify:track:0pX5IztL39thiVjIlb2ksW",
    "imageUrl": "https://i.scdn.co/image/ab67616d0000b2737f1ff8e8be3727f0c362ba06"
  },
  {
    "timestamp": 1763170144886,
    "user": "Rezz",
    "userId": "spotify:user:31ilktz5fqv575vybtkzthcniyqu",
    "track": "Mendarah",
    "artist": "Nadin Amizah",
    "uri": "spotify:track:75OokMC3JzPnRNXcLTAKdr",
    "imageUrl": "https://i.scdn.co/image/ab67616d0000b2736d57a5c60decaa8fb39d5afb"
  },
  {
    "timestamp": 1763169905271,
    "user": "Rezz",
    "userId": "spotify:user:31ilktz5fqv575vybtkzthcniyqu",
    "track": "Jalan Pulang",
    "artist": "Yura Yunita",
    "uri": "spotify:track:1ado6H8nwj0izGVinobwuP",
    "imageUrl": "https://i.scdn.co/image/ab67616d0000b273c30403575b8ba72515ed1dc2"
  },
  {
    "timestamp": 1763169698308,
    "user": "Rezz",
    "userId": "spotify:user:31ilktz5fqv575vybtkzthcniyqu",
    "track": "Berakhir di Aku - Original Soundtrack From \"Home Sweet Loan\"",
    "artist": "Idgitaf",
    "uri": "spotify:track:3KcfLN50nMGR4uH1T0QVxL",
    "imageUrl": "https://i.scdn.co/image/ab67616d0000b2734ae1c2813cfa6d10c73f4661"
  },
  {
    "timestamp": 1763169455048,
    "user": "Rezz",
    "userId": "spotify:user:31ilktz5fqv575vybtkzthcniyqu",
    "track": "Percik Kecil",
    "artist": "Bernadya, JKT48",
    "uri": "spotify:track:6CsSNFkQVVuQjRQMrzyDzq",
    "imageUrl": "https://i.scdn.co/image/ab67616d0000b27391389f69b393611aff87a6ac"
  },
  {
    "timestamp": 1763169215234,
    "user": "Rezz",
    "userId": "spotify:user:31ilktz5fqv575vybtkzthcniyqu",
    "track": "Yasudah",
    "artist": "Sal Priadi",
    "uri": "spotify:track:3qhj6auEMIDhJv6oCHI9fJ",
    "imageUrl": "https://i.scdn.co/image/ab67616d0000b273686acaaa87bfc6ebb42b3bd2"
  },
  {
    "timestamp": 1763168914985,
    "user": "Rezz",
    "userId": "spotify:user:31ilktz5fqv575vybtkzthcniyqu",
    "track": "Engga Ngerti",
    "artist": "Kahitna",
    "uri": "spotify:track:5yk8nFAFWgN6Y6yevZX2ht",
    "imageUrl": "https://i.scdn.co/image/ab67616d0000b273d26766e9cb90e87d4faea236"
  },
  {
    "timestamp": 1763168674975,
    "user": "Rezz",
    "userId": "spotify:user:31ilktz5fqv575vybtkzthcniyqu",
    "track": "Rumpang",
    "artist": "Nadin Amizah",
    "uri": "spotify:track:2TRGNVokPnC2a2oHg5iv1H",
    "imageUrl": "https://i.scdn.co/image/ab67616d0000b27397068c79ef4ad5a7643ef94a"
  },
  {
    "timestamp": 1763168344928,
    "user": "Rezz",
    "userId": "spotify:user:31ilktz5fqv575vybtkzthcniyqu",
    "track": "Tenang",
    "artist": "Yura Yunita",
    "uri": "spotify:track:7lr82r1RMJudgcKQ8y7H9K",
    "imageUrl": "https://i.scdn.co/image/ab67616d0000b27368d7905b0548a6c9ba21b638"
  },
  {
    "timestamp": 1763168106766,
    "user": "Rezz",
    "userId": "spotify:user:31ilktz5fqv575vybtkzthcniyqu",
    "track": "Sinyal-Sinyal",
    "artist": "Bernadya",
    "uri": "spotify:track:2VjlTuNUGwJJCch2XtUnrb",
    "imageUrl": "https://i.scdn.co/image/ab67616d0000b273cb1e5f7d0942bf9196c1e711"
  },
  {
    "timestamp": 1763167865028,
    "user": "Rezz",
    "userId": "spotify:user:31ilktz5fqv575vybtkzthcniyqu",
    "track": "Rehat",
    "artist": "Kunto Aji",
    "uri": "spotify:track:7mjO4RbTZIb1SfE8G673Lm",
    "imageUrl": "https://i.scdn.co/image/ab67616d0000b273b7d74c7fa660999ad4ff0e8d"
  },
  {
    "timestamp": 1763167505250,
    "user": "Rezz",
    "userId": "spotify:user:31ilktz5fqv575vybtkzthcniyqu",
    "track": "Mantan Terindah",
    "artist": "Yovie Widianto, Raisa",
    "uri": "spotify:track:1wE4Iqv0tXXuZBA67PoGvw",
    "imageUrl": "https://i.scdn.co/image/ab67616d0000b27395f411458f0d6ee98424bf6c"
  },
  {
    "timestamp": 1763167294922,
    "user": "Rezz",
    "userId": "spotify:user:31ilktz5fqv575vybtkzthcniyqu",
    "track": "Kusut",
    "artist": "Fourtwnty",
    "uri": "spotify:track:3diD8b3u6oEn74BezQpujj",
    "imageUrl": "https://i.scdn.co/image/ab67616d0000b27395d6a28dfd9d8da037c142df"
  },
  {
    "timestamp": 1763167073806,
    "user": "Rezz",
    "userId": "spotify:user:31ilktz5fqv575vybtkzthcniyqu",
    "track": "Angin Rindu",
    "artist": "Rony Parulian",
    "uri": "spotify:track:7i5S9v9fiN6Vuqy5Hf9KbR",
    "imageUrl": "https://i.scdn.co/image/ab67616d0000b27357124131195ac118b99d2042"
  },
  {
    "timestamp": 1763166785075,
    "user": "Rezz",
    "userId": "spotify:user:31ilktz5fqv575vybtkzthcniyqu",
    "track": "Berlari",
    "artist": "Bernadya",
    "uri": "spotify:track:3xQx7JqDSUk8q36W68BVEM",
    "imageUrl": "https://i.scdn.co/image/ab67616d0000b27327693aaf059002bba3a7655a"
  },
  {
    "timestamp": 1763166572412,
    "user": "Rezz",
    "userId": "spotify:user:31ilktz5fqv575vybtkzthcniyqu",
    "track": "Sialnya, Hidup Harus Tetap Berjalan",
    "artist": "Bernadya",
    "uri": "spotify:track:7Lm4S2P0MHwBktcdNILLQA",
    "imageUrl": "https://i.scdn.co/image/ab67616d0000b27327693aaf059002bba3a7655a"
  },
  {
    "timestamp": 1763166530309,
    "user": "Rezz",
    "userId": "spotify:user:31ilktz5fqv575vybtkzthcniyqu",
    "track": "Berlari",
    "artist": "Bernadya",
    "uri": "spotify:track:3xQx7JqDSUk8q36W68BVEM",
    "imageUrl": "https://i.scdn.co/image/ab67616d0000b27327693aaf059002bba3a7655a"
  },
  {
    "timestamp": 1763166521377,
    "user": "Rezz",
    "userId": "spotify:user:31ilktz5fqv575vybtkzthcniyqu",
    "track": "Lama-Lama",
    "artist": "Bernadya",
    "uri": "spotify:track:0pmyq5KBXP3agRdxl1SZXx",
    "imageUrl": "https://i.scdn.co/image/ab67616d0000b27327693aaf059002bba3a7655a"
  },
  {
    "timestamp": 1763166313806,
    "user": "Rezz",
    "userId": "spotify:user:31ilktz5fqv575vybtkzthcniyqu",
    "track": "Terlintas",
    "artist": "Bernadya",
    "uri": "spotify:track:22Psd9lrrgVbTERHCGo7i1",
    "imageUrl": "https://i.scdn.co/image/ab67616d0000b273cb1e5f7d0942bf9196c1e711"
  },
  {
    "timestamp": 1763166101106,
    "user": "Rezz",
    "userId": "spotify:user:31ilktz5fqv575vybtkzthcniyqu",
    "track": "Berlari",
    "artist": "Bernadya",
    "uri": "spotify:track:3xQx7JqDSUk8q36W68BVEM",
    "imageUrl": "https://i.scdn.co/image/ab67616d0000b27327693aaf059002bba3a7655a"
  },
  {
    "timestamp": 1763165584142,
    "user": "Rezz",
    "userId": "spotify:user:31ilktz5fqv575vybtkzthcniyqu",
    "track": "Berlari",
    "artist": "Bernadya",
    "uri": "spotify:track:3xQx7JqDSUk8q36W68BVEM",
    "imageUrl": "https://i.scdn.co/image/ab67616d0000b27327693aaf059002bba3a7655a"
  },
  {
    "timestamp": 1763164876282,
    "user": "Rezz",
    "userId": "spotify:user:31ilktz5fqv575vybtkzthcniyqu",
    "track": "Untungnya, Hidup Harus Tetap Berjalan",
    "artist": "Bernadya",
    "uri": "spotify:track:2gcMYiZzzmzoF8PPAfL3IO",
    "imageUrl": "https://i.scdn.co/image/ab67616d0000b27327693aaf059002bba3a7655a"
  },
  {
    "timestamp": 1763164696553,
    "user": "Rezz",
    "userId": "spotify:user:31ilktz5fqv575vybtkzthcniyqu",
    "track": "Apa Mungkin",
    "artist": "Bernadya",
    "uri": "spotify:track:4LUHc4MWBOvDCjWNUQhTkT",
    "imageUrl": "https://i.scdn.co/image/ab67616d0000b273cb1e5f7d0942bf9196c1e711"
  },
  {
    "timestamp": 1763164459164,
    "user": "Rezz",
    "userId": "spotify:user:31ilktz5fqv575vybtkzthcniyqu",
    "track": "Kata Mereka Ini Berlebihan",
    "artist": "Bernadya",
    "uri": "spotify:track:6wj06az0WX7fClA2w319dO",
    "imageUrl": "https://i.scdn.co/image/ab67616d0000b27327693aaf059002bba3a7655a"
  },
  {
    "timestamp": 1763164276269,
    "user": "Rezz",
    "userId": "spotify:user:31ilktz5fqv575vybtkzthcniyqu",
    "track": "Kini Mereka Tahu",
    "artist": "Bernadya",
    "uri": "spotify:track:0UFYW8XaNvO6K8yZLMHPkB",
    "imageUrl": "https://i.scdn.co/image/ab67616d0000b27327693aaf059002bba3a7655a"
  },
  {
    "timestamp": 1763163979155,
    "user": "Rezz",
    "userId": "spotify:user:31ilktz5fqv575vybtkzthcniyqu",
    "track": "Masa Sepi",
    "artist": "Bernadya",
    "uri": "spotify:track:4rXtQ0AKr3gOQQW5UKZSHP",
    "imageUrl": "https://i.scdn.co/image/ab67616d0000b273cb1e5f7d0942bf9196c1e711"
  },
  {
    "timestamp": 1763163767526,
    "user": "Rezz",
    "userId": "spotify:user:31ilktz5fqv575vybtkzthcniyqu",
    "track": "Ambang Pintu",
    "artist": "Bernadya",
    "uri": "spotify:track:4piQOnMesAkS5X0ugzHiBS",
    "imageUrl": "https://i.scdn.co/image/ab67616d0000b27327693aaf059002bba3a7655a"
  },
  {
    "timestamp": 1763163586109,
    "user": "Rezz",
    "userId": "spotify:user:31ilktz5fqv575vybtkzthcniyqu",
    "track": "Asumsi",
    "artist": "Adrian Khalif, Bernadya",
    "uri": "spotify:track:72DL0kjCGfA4qIDQnR88hT",
    "imageUrl": "https://i.scdn.co/image/ab67616d0000b2739670851bed73df294eee9111"
  },
  {
    "timestamp": 1763163318962,
    "user": "Rezz",
    "userId": "spotify:user:31ilktz5fqv575vybtkzthcniyqu",
    "track": "Satu Bulan",
    "artist": "Bernadya",
    "uri": "spotify:track:7zOVh5fGpEwSbZd0g9z80B",
    "imageUrl": "https://i.scdn.co/image/ab67616d0000b273cb1e5f7d0942bf9196c1e711"
  }
]