[
  {
    "timestamp": 1778713217676,
    "user": "Rezz",
    "userId": "spotify:user:31ilktz5fqv575vybtkzthcniyqu",
    "track": "Biar Mantan Tau",
    "artist": "3 Composers",
    "uri": "spotify:track:6E6OhmmXOkklCcbqq7XF88",
    "imageUrl": "https://i.scdn.co/image/ab67616d0000b273385b87a9259a6139d7138e71"
  },
  {
    "timestamp": 1778713007507,
    "user": "Rezz",
    "userId": "spotify:user:31ilktz5fqv575vybtkzthcniyqu",
    "track": "Pergi Tak Meninggalkan",
    "artist": "Ekhsan",
    "uri": "spotify:track:49AwlI4CRKl7HPyCxPSTOV",
    "imageUrl": "https://i.scdn.co/image/ab67616d0000b273d93468a32845c4778d7ebce1"
  },
  {
    "timestamp": 1778712767707,
    "user": "Rezz",
    "userId": "spotify:user:31ilktz5fqv575vybtkzthcniyqu",
    "track": "Dirimu Satu - From \"My Lecturer My Husband 2\"",
    "artist": "Rizky Febian",
    "uri": "spotify:track:4elchSBwiSlTEhNc490QHu",
    "imageUrl": "https://i.scdn.co/image/ab67616d0000b273a8ce9e6636f5cac4c5825445"
  },
  {
    "timestamp": 1778712527497,
    "user": "Rezz",
    "userId": "spotify:user:31ilktz5fqv575vybtkzthcniyqu",
    "track": "Cinta Terakhirku",
    "artist": "Arsy Widianto, Syifa Hadju",
    "uri": "spotify:track:5bLIFHq7N4yqz8LX3wwD4E",
    "imageUrl": "https://i.scdn.co/image/ab67616d0000b27384e3ae9f04f3e41302abb841"
  },
  {
    "timestamp": 1778712257517,
    "user": "Rezz",
    "userId": "spotify:user:31ilktz5fqv575vybtkzthcniyqu",
    "track": "Tampar",
    "artist": "Juicy Luicy",
    "uri": "spotify:track:2RHm5IDIZ8fYRGzBIo7exV",
    "imageUrl": "https://i.scdn.co/image/ab67616d0000b273895ef71f3b84221075ac06f5"
  },
  {
    "timestamp": 1778712047533,
    "user": "Rezz",
    "userId": "spotify:user:31ilktz5fqv575vybtkzthcniyqu",
    "track": "Aminlah Bersamaku",
    "artist": "Rizky Febian",
    "uri": "spotify:track:76cS2H0n1Pt9eUTMbW05TL",
    "imageUrl": "https://i.scdn.co/image/ab67616d0000b273acbab532d239c133a83a5815"
  },
  {
    "timestamp": 1778711837804,
    "user": "Rezz",
    "userId": "spotify:user:31ilktz5fqv575vybtkzthcniyqu",
    "track": "Jarak",
    "artist": "Mario G klau",
    "uri": "spotify:track:0gatw2EDPKF5rACFRjPO8g",
    "imageUrl": "https://i.scdn.co/image/ab67616d0000b27389982fdc9d5781b9cfe46eee"
  },
  {
    "timestamp": 1778709522077,
    "user": "Rezz",
    "userId": "spotify:user:31ilktz5fqv575vybtkzthcniyqu",
    "track": "I Just Couldn't Save You Tonight - Story of Kale - Original Motion Picture Soundtrack",
    "artist": "Ardhito Pramono, Aurélie",
    "uri": "spotify:track:5AkV53fo1u01mi8r22JNeF",
    "imageUrl": "https://i.scdn.co/image/ab67616d0000b27379541996457d9d06cf9806e3"
  }
]