{
  "friends": [
    {
      "timestamp": 1763130647711,
      "user": {
        "uri": "spotify:user:31ilktz5fqv575vybtkzthcniyqu",
        "name": "Rezz",
        "imageUrl": "https://i.scdn.co/image/ab6775700000ee85dde166d5c9c10ad2277bd9c5"
      },
      "track": {
        "uri": "spotify:track:7BVtNEGHh8O2kLyciokFyl",
        "name": "Teganya Kau",
        "imageUrl": "https://i.scdn.co/image/ab67616d0000b273ab5d3c815265b9b11b51ed86",
        "album": {
          "uri": "spotify:album:2MNxWXky396sx7AEf71fsE",
          "name": "Teganya Kau"
        },
        "artist": {
          "uri": "spotify:artist:6Sv2jkzH9sWQjwghW5ArMG",
          "name": "Lyodra"
        },
        "context": {
          "uri": "spotify:playlist:37i9dQZF1DX7sD2LU79ZzQ",
          "name": "playlist",
          "index": 0
        }
      }
    }
  ]
}