{
  "friends": [
    {
      "timestamp": 1763463003946,
      "user": {
        "uri": "spotify:user:31ilktz5fqv575vybtkzthcniyqu",
        "name": "Rezz",
        "imageUrl": "https://i.scdn.co/image/ab6775700000ee85dde166d5c9c10ad2277bd9c5"
      },
      "track": {
        "uri": "spotify:track:3Puhw21QI2MKR4rdvyPuIb",
        "name": "ours to keep",
        "imageUrl": "https://i.scdn.co/image/ab67616d0000b27341f65131e6205f8deac33651",
        "album": {
          "uri": "spotify:album:5vvuakA6CVikfUwArrorTd",
          "name": "DISCO"
        },
        "artist": {
          "uri": "spotify:artist:5HLrlI5LdULY9s740CsAFZ",
          "name": "Kendis, adis"
        },
        "context": {
          "uri": "spotify:playlist:37i9dQZF1DXa2EiKmMLhFD",
          "name": "playlist",
          "index": 0
        }
      }
    }
  ]
}